autowaterqualitymodeler/__init__.py
autowaterqualitymodeler/_version.py
autowaterqualitymodeler/config/__init__.py
autowaterqualitymodeler/config/features_config.py
autowaterqualitymodeler/config/system_config.py
autowaterqualitymodeler/core/__init__.py
autowaterqualitymodeler/core/config.py
autowaterqualitymodeler/core/exceptions.py
autowaterqualitymodeler/core/model.py
autowaterqualitymodeler/core/modeler.py
autowaterqualitymodeler/core/types.py
autowaterqualitymodeler/features/__init__.py
autowaterqualitymodeler/features/calculator.py
autowaterqualitymodeler/features/selector.py
autowaterqualitymodeler/models/__init__.py
autowaterqualitymodeler/models/combiner.py
autowaterqualitymodeler/models/linear_fitter.py
autowaterqualitymodeler/models/power_fitter.py
autowaterqualitymodeler/pipeline/__init__.py
autowaterqualitymodeler/pipeline/auto_pipeline.py
autowaterqualitymodeler/pipeline/formatter.py
autowaterqualitymodeler/pipeline/tuning_pipeline.py
autowaterqualitymodeler/preprocessing/__init__.py
autowaterqualitymodeler/preprocessing/spectrum_processor.py
autowaterqualitymodeler/resources/D65xCIE.xlsx
autowaterqualitymodeler/resources/__init__.py
autowaterqualitymodeler/utils/__init__.py
autowaterqualitymodeler/utils/encryption.py
autowaterqualitymodeler-4.7.2.dist-info/licenses/LICENSE
autowaterqualitymodeler-4.7.2.dist-info/METADATA
autowaterqualitymodeler-4.7.2.dist-info/WHEEL
autowaterqualitymodeler-4.7.2.dist-info/top_level.txt
autowaterqualitymodeler-4.7.2.dist-info/RECORD
