Metadata-Version: 2.4
Name: autowaterqualitymodeler
Version: 4.7.2
Summary: Automatic water quality spectral modeling tool
Author-email: 周元琦 <zyq1034378361@gmail.com>
Classifier: Development Status :: 3 - Alpha
Classifier: Intended Audience :: Science/Research
Classifier: Topic :: Scientific/Engineering :: GIS
Classifier: Programming Language :: Python :: 3
Classifier: Programming Language :: Python :: 3.10
Requires-Python: >=3.10
License-File: LICENSE
Requires-Dist: pandas>=1.3.0
Requires-Dist: numpy>=1.21.0
Requires-Dist: scipy>=1.7.0
Requires-Dist: scikit-learn>=1.0.0
Requires-Dist: openpyxl>=3.0.0
Requires-Dist: cryptography>=41.0.0
Requires-Dist: matplotlib>=3.10.3
Requires-Dist: seaborn>=0.13.2
Provides-Extra: dev
Requires-Dist: pytest>=7.0.0; extra == "dev"
Requires-Dist: pytest-cov>=4.0.0; extra == "dev"
Requires-Dist: pytest-mock>=3.0.0; extra == "dev"
Requires-Dist: black>=22.0.0; extra == "dev"
Requires-Dist: flake8>=4.0.0; extra == "dev"
Requires-Dist: mypy>=0.950; extra == "dev"
Requires-Dist: isort>=5.0.0; extra == "dev"
Requires-Dist: pre-commit>=2.0.0; extra == "dev"
Requires-Dist: basedpyright>=1.10.0; extra == "dev"
Requires-Dist: pandas-stubs>=1.5.0; extra == "dev"
Requires-Dist: setuptools_scm>=6.2; extra == "dev"
Dynamic: license-file
